Workbook

Sheet Dashboard
A1: FINANCIAL DASHBOARD
A4: OVERVIEW
A5: Total Income | B5: Total Expenses | C5: Current Balance
A6: =SUMIF(Transactions!C:C, "income", Transactions!E:E) -> 80000000 | B6: =SUMIF(Transactions!C:C, "expense", Transactions!E:E) -> 25650000 | C6: =A6 - B6 -> 54350000
A9: ACTIVE BUDGET TRACKER
A10: Budget Title | B10: Category | C10: Start Date | D10: End Date | E10: Allocated | F10: Spent | G10: Remaining | H10: Status
A11: =IF(Budgets!B2="","",Budgets!B2) -> Main | B11: =IF(Budgets!C2="","",Budgets!C2) -> Hiburan | C11: =IF(Budgets!E2="","",Budgets!E2) -> 46204 | D11: =IF(Budgets!F2="","",Budgets!F2) -> 46234 | E11: =IF(Budgets!D2="","",Budgets!D2) -> 50000000 | F11: =IF(A11="","",SUMIFS(Transactions!E:E, Transactions!D:D, B11, Transactions!C:C, "expense", Transactions!B:B, ">="&C11, Transactions!B:B, "<="&D11)) -> 25400000 | G11: =IF(A11="","",E11-F11) -> 24600000 | H11: =IF(A11="","",IF(G11<0, "OVER BUDGET", IF(G11<=E11*0.2, "LOW", "GOOD"))) -> GOOD
A12: =IF(Budgets!B3="","",Budgets!B3) -> Transportasi | B12: =IF(Budgets!C3="","",Budgets!C3) -> Transport | C12: =IF(Budgets!E3="","",Budgets!E3) -> 46204 | D12: =IF(Budgets!F3="","",Budgets!F3) -> 46234 | E12: =IF(Budgets!D3="","",Budgets!D3) -> 5000000 | F12: =IF(A12="","",SUMIFS(Transactions!E:E, Transactions!D:D, B12, Transactions!C:C, "expense", Transactions!B:B, ">="&C12, Transactions!B:B, "<="&D12)) -> 250000 | G12: =IF(A12="","",E12-F12) -> 4750000 | H12: =IF(A12="","",IF(G12<0, "OVER BUDGET", IF(G12<=E12*0.2, "LOW", "GOOD"))) -> GOOD
A13: =IF(Budgets!B4="","",Budgets!B4) | B13: =IF(Budgets!C4="","",Budgets!C4) | C13: =IF(Budgets!E4="","",Budgets!E4) | D13: =IF(Budgets!F4="","",Budgets!F4) | E13: =IF(Budgets!D4="","",Budgets!D4) | F13: =IF(A13="","",SUMIFS(Transactions!E:E, Transactions!D:D, B13, Transactions!C:C, "expense", Transactions!B:B, ">="&C13, Transactions!B:B, "<="&D13)) | G13: =IF(A13="","",E13-F13) | H13: =IF(A13="","",IF(G13<0, "OVER BUDGET", IF(G13<=E13*0.2, "LOW", "GOOD")))
A14: =IF(Budgets!B5="","",Budgets!B5) | B14: =IF(Budgets!C5="","",Budgets!C5) | C14: =IF(Budgets!E5="","",Budgets!E5) | D14: =IF(Budgets!F5="","",Budgets!F5) | E14: =IF(Budgets!D5="","",Budgets!D5) | F14: =IF(A14="","",SUMIFS(Transactions!E:E, Transactions!D:D, B14, Transactions!C:C, "expense", Transactions!B:B, ">="&C14, Transactions!B:B, "<="&D14)) | G14: =IF(A14="","",E14-F14) | H14: =IF(A14="","",IF(G14<0, "OVER BUDGET", IF(G14<=E14*0.2, "LOW", "GOOD")))
A15: =IF(Budgets!B6="","",Budgets!B6) | B15: =IF(Budgets!C6="","",Budgets!C6) | C15: =IF(Budgets!E6="","",Budgets!E6) | D15: =IF(Budgets!F6="","",Budgets!F6) | E15: =IF(Budgets!D6="","",Budgets!D6) | F15: =IF(A15="","",SUMIFS(Transactions!E:E, Transactions!D:D, B15, Transactions!C:C, "expense", Transactions!B:B, ">="&C15, Transactions!B:B, "<="&D15)) | G15: =IF(A15="","",E15-F15) | H15: =IF(A15="","",IF(G15<0, "OVER BUDGET", IF(G15<=E15*0.2, "LOW", "GOOD")))
A16: =IF(Budgets!B7="","",Budgets!B77) | B16: =IF(Budgets!C7="","",Budgets!C77) | C16: =IF(Budgets!E7="","",Budgets!E7) | D16: =IF(Budgets!F7="","",Budgets!F7) | E16: =IF(Budgets!D7="","",Budgets!D7) | F16: =IF(A16="","",SUMIFS(Transactions!E:E, Transactions!D:D, B16, Transactions!C:C, "expense", Transactions!B:B, ">="&C16, Transactions!B:B, "<="&D16)) | G16: =IF(A16="","",E16-F16) | H16: =IF(A16="","",IF(G16<0, "OVER BUDGET", IF(G16<=E16*0.2, "LOW", "GOOD")))
A17: =IF(Budgets!B8="","",Budgets!B8) | B17: =IF(Budgets!C8="","",Budgets!C8) | C17: =IF(Budgets!E8="","",Budgets!E8) | D17: =IF(Budgets!F8="","",Budgets!F8) | E17: =IF(Budgets!D8="","",Budgets!D8) | F17: =IF(A17="","",SUMIFS(Transactions!E:E, Transactions!D:D, B17, Transactions!C:C, "expense", Transactions!B:B, ">="&C17, Transactions!B:B, "<="&D17)) | G17: =IF(A17="","",E17-F17) | H17: =IF(A17="","",IF(G17<0, "OVER BUDGET", IF(G17<=E17*0.2, "LOW", "GOOD")))
A18: =IF(Budgets!B9="","",Budgets!B9) | B18: =IF(Budgets!C9="","",Budgets!C9) | C18: =IF(Budgets!E9="","",Budgets!E9) | D18: =IF(Budgets!F9="","",Budgets!F9) | E18: =IF(Budgets!D9="","",Budgets!D9) | F18: =IF(A18="","",SUMIFS(Transactions!E:E, Transactions!D:D, B18, Transactions!C:C, "expense", Transactions!B:B, ">="&C18, Transactions!B:B, "<="&D18)) | G18: =IF(A18="","",E18-F18) | H18: =IF(A18="","",IF(G18<0, "OVER BUDGET", IF(G18<=E18*0.2, "LOW", "GOOD")))
A19: =IF(Budgets!B10="","",Budgets!B10) | B19: =IF(Budgets!C10="","",Budgets!C10) | C19: =IF(Budgets!E10="","",Budgets!E10) | D19: =IF(Budgets!F10="","",Budgets!F10) | E19: =IF(Budgets!D10="","",Budgets!D10) | F19: =IF(A19="","",SUMIFS(Transactions!E:E, Transactions!D:D, B19, Transactions!C:C, "expense", Transactions!B:B, ">="&C19, Transactions!B:B, "<="&D19)) | G19: =IF(A19="","",E19-F19) | H19: =IF(A19="","",IF(G19<0, "OVER BUDGET", IF(G19<=E19*0.2, "LOW", "GOOD")))
A20: =IF(Budgets!B11="","",Budgets!B11) | B20: =IF(Budgets!C11="","",Budgets!C11) | C20: =IF(Budgets!E11="","",Budgets!E11) | D20: =IF(Budgets!F11="","",Budgets!F11) | E20: =IF(Budgets!D11="","",Budgets!D11) | F20: =IF(A20="","",SUMIFS(Transactions!E:E, Transactions!D:D, B20, Transactions!C:C, "expense", Transactions!B:B, ">="&C20, Transactions!B:B, "<="&D20)) | G20: =IF(A20="","",E20-F20) | H20: =IF(A20="","",IF(G20<0, "OVER BUDGET", IF(G20<=E20*0.2, "LOW", "GOOD")))
A23: EXPENSE BREAKDOWN
A24: Category | B24: Total Spent
A25: Makanan | B25: =SUMIFS(Transactions!E:E, Transactions!C:C, "expense", Transactions!D:D, A25) -> 0
A26: Transport | B26: =SUMIFS(Transactions!E:E, Transactions!C:C, "expense", Transactions!D:D, A26) -> 250000
A27: Belanja | B27: =SUMIFS(Transactions!E:E, Transactions!C:C, "expense", Transactions!D:D, A27) -> 0
A28: Hiburan | B28: =SUMIFS(Transactions!E:E, Transactions!C:C, "expense", Transactions!D:D, A28) -> 25400000
A29: Kesehatan | B29: =SUMIFS(Transactions!E:E, Transactions!C:C, "expense", Transactions!D:D, A29) -> 0
A30: Tagihan | B30: =SUMIFS(Transactions!E:E, Transactions!C:C, "expense", Transactions!D:D, A30) -> 0
A31: Pendidikan | B31: =SUMIFS(Transactions!E:E, Transactions!C:C, "expense", Transactions!D:D, A31) -> 0
A32: Gaji | B32: =SUMIFS(Transactions!E:E, Transactions!C:C, "expense", Transactions!D:D, A32) -> 0
A33: Freelance | B33: =SUMIFS(Transactions!E:E, Transactions!C:C, "expense", Transactions!D:D, A33) -> 0
A34: Investasi | B34: =SUMIFS(Transactions!E:E, Transactions!C:C, "expense", Transactions!D:D, A34) -> 0
A35: Hadiah | B35: =SUMIFS(Transactions!E:E, Transactions!C:C, "expense", Transactions!D:D, A35) -> 0
A36: Lainnya | B36: =SUMIFS(Transactions!E:E, Transactions!C:C, "expense", Transactions!D:D, A36) -> 0

Sheet Transactions
A1: id | B1: data | C1: type | D1: category | E1: amount | F1: description | G1: created | H1: updated
A2: b382be401e714508b247 | B2: 46226 | C2: income | D2: Gaji | E2: 30000000 | F2: Gaji | G2: 2026-07-23T03:15:38.281Z | H2: 2026-07-23T04:58:16.860Z
A3: 018e34895b6e41f19d3d | B3: 46226 | C3: expense | D3: Hiburan | E3: 200000 | F3: Main Keluar | G3: 2026-07-23T08:09:26.498Z | H3: 2026-07-23T08:09:26.498Z
A4: b59724cad0e1429e910f | B4: 46227 | C4: expense | D4: Hiburan | E4: 200000 | F4: Liburan | G4: 2026-07-24T05:49:54.933Z | H4: 2026-07-24T05:49:54.933Z
A5: 1fba99d940704a3e9ad0 | B5: 46228 | C5: expense | D5: Hiburan | E5: 25000000 | F5: Main Ke Jepang | G5: 2026-07-24T06:25:37.330Z | H5: 2026-07-24T06:25:37.330Z
A6: 47afeadbeb3641a28465 | B6: 46227 | C6: income | D6: Gaji | E6: 50000000 | F6: Gajian | G6: 2026-07-24T06:28:36.416Z | H6: 2026-07-24T06:28:36.416Z
A7: 78dc8bd2202c4eab84fe | B7: 46227 | C7: expense | D7: Transport | E7: 250000 | F7: Naik Kereta | G7: 2026-07-24T06:29:55.547Z | H7: 2026-07-24T06:29:55.547Z

Sheet Budgets
A1: id | B1: title | C1: linked_category | D1: amount | E1: period_start | F1: period_end | G1: created | H1: updated
A2: b380517fafda456991f0 | B2: Main | C2: Hiburan | D2: 50000000 | E2: 46204 | F2: 46234 | G2: 2026-07-23T09:22:08.447Z | H2: 2026-07-23T09:22:08.447Z
A3: 5936d4b92a5145a7bea0 | B3: Transportasi | C3: Transport | D3: 5000000 | E3: 46204 | F3: 46234 | G3: 2026-07-24T06:27:07.593Z | H3: 2026-07-24T06:27:07.593Z
